pxr/__init__.py
pxr/tbb.dll
pxr/tbb_debug.dll
pxr/tbb_preview.dll
pxr/tbb_preview_debug.dll
pxr/tbbbind.dll
pxr/tbbbind_debug.dll
pxr/tbbmalloc.dll
pxr/tbbmalloc_debug.dll
pxr/tbbmalloc_proxy.dll
pxr/tbbmalloc_proxy_debug.dll
pxr/usd_ms.dll
pxr/Ar/__init__.py
pxr/Ar/_ar.pyd
pxr/Gf/__init__.py
pxr/Gf/_gf.pyd
pxr/Kind/__init__.py
pxr/Kind/_kind.pyd
pxr/Pcp/__init__.py
pxr/Pcp/_pcp.pyd
pxr/Plug/__init__.py
pxr/Plug/_plug.pyd
pxr/Sdf/__init__.py
pxr/Sdf/_sdf.pyd
pxr/Sdr/__init__.py
pxr/Sdr/_sdr.pyd
pxr/Sdr/shaderParserTestUtils.py
pxr/Tf/__init__.py
pxr/Tf/_tf.pyd
pxr/Tf/testenv/__init__.py
pxr/Tf/testenv/testTfPyInvoke_callees.py
pxr/Tf/testenv/testTfScriptModuleLoader_AAA_RaisesError.py
pxr/Tf/testenv/testTfScriptModuleLoader_DepLoadsAll.py
pxr/Tf/testenv/testTfScriptModuleLoader_LoadsAll.py
pxr/Tf/testenv/testTfScriptModuleLoader_LoadsUnknown.py
pxr/Tf/testenv/testTfScriptModuleLoader_Other.py
pxr/Tf/testenv/testTfScriptModuleLoader_Test.py
pxr/Tf/testenv/testTfScriptModuleLoader_Unknown.py
pxr/Trace/__init__.py
pxr/Trace/__main__.py
pxr/Trace/_trace.pyd
pxr/Ts/__init__.py
pxr/Ts/_ts.pyd
pxr/Usd/__init__.py
pxr/Usd/_usd.pyd
pxr/Usd/usdGenSchema.py
pxr/Usd/usdInitSchema.py
pxr/UsdGeom/__init__.py
pxr/UsdGeom/_usdGeom.pyd
pxr/UsdHydra/__init__.py
pxr/UsdHydra/_usdHydra.pyd
pxr/UsdLux/__init__.py
pxr/UsdLux/_usdLux.pyd
pxr/UsdMedia/__init__.py
pxr/UsdMedia/_usdMedia.pyd
pxr/UsdPhysics/__init__.py
pxr/UsdPhysics/_usdPhysics.pyd
pxr/UsdProc/__init__.py
pxr/UsdProc/_usdProc.pyd
pxr/UsdRender/__init__.py
pxr/UsdRender/_usdRender.pyd
pxr/UsdRi/__init__.py
pxr/UsdRi/_usdRi.pyd
pxr/UsdSemantics/__init__.py
pxr/UsdSemantics/_usdSemantics.pyd
pxr/UsdShade/__init__.py
pxr/UsdShade/_usdShade.pyd
pxr/UsdShaders/__init__.py
pxr/UsdSkel/__init__.py
pxr/UsdSkel/_usdSkel.pyd
pxr/UsdUI/__init__.py
pxr/UsdUI/_usdUI.pyd
pxr/UsdUtils/__init__.py
pxr/UsdUtils/_usdUtils.pyd
pxr/UsdUtils/complianceChecker.py
pxr/UsdUtils/constantsGroup.py
pxr/UsdUtils/fixBrokenPixarSchemas.py
usd_core-25.11.dist-info/LICENSE.txt
usd_core-25.11.dist-info/METADATA
usd_core-25.11.dist-info/WHEEL
usd_core-25.11.dist-info/top_level.txt
usd_core-25.11.dist-info/RECORD
