Metadata-Version: 2.1
Name: usd-core
Version: 25.11
Summary: Pixar's Universal Scene Description
Home-page: https://openusd.org
Author: Pixar Animation Studios
Author-email: openusd+usd_pypi@pixar.com
License: LicenseRef-TOST-1.0
Project-URL: Documentation, https://openusd.org
Project-URL: Developer Docs, https://www.openusd.org/release/apiDocs.html
Project-URL: Source, https://github.com/PixarAnimationStudios/OpenUSD
Project-URL: Discussion Group, https://forum.openusd.org
Platform: UNKNOWN
Classifier: Programming Language :: Python :: 3
Classifier: Operating System :: POSIX :: Linux
Classifier: Operating System :: MacOS :: MacOS X
Classifier: Operating System :: Microsoft :: Windows :: Windows 10
Classifier: Environment :: Console
Classifier: Topic :: Multimedia :: Graphics
Requires-Python: >=3.8, <3.14
License-File: LICENSE.txt
